tests/__init__.py
tests/test_group_view.py
tests/test_icon_views.py
wagtail_icons/__init__.py
wagtail_icons/admin_urls.py
wagtail_icons/apps.py
wagtail_icons/blocks.py
wagtail_icons/edit_handlers.py
wagtail_icons/fields.py
wagtail_icons/forms.py
wagtail_icons/wagtail_hooks.py
wagtail_icons/widgets.py
wagtail_icons/migrations/0001_initial.py
wagtail_icons/migrations/__init__.py
wagtail_icons/models/__init__.py
wagtail_icons/models/group.py
wagtail_icons/models/upload.py
wagtail_icons/static/wagtail_icons/js/add_group.js
wagtail_icons/static/wagtail_icons/js/add_icon.js
wagtail_icons/static/wagtail_icons/js/edit.js
wagtail_icons/static/wagtail_icons/js/groups.js
wagtail_icons/static/wagtail_icons/js/icon_chooser_modal.js
wagtail_icons/static/wagtail_icons/js/iconchooser.js
wagtail_icons/static/wagtail_icons/js/index.js
wagtail_icons/static/wagtail_icons/style/add.css
wagtail_icons/static/wagtail_icons/style/groups.css
wagtail_icons/static/wagtail_icons/style/iconchooser.css
wagtail_icons/static/wagtail_icons/style/index.css
wagtail_icons/static/wagtail_icons/style/pagination.css
wagtail_icons/templates/wagtail_icons/pagination.html
wagtail_icons/templates/wagtail_icons/groups/add.html
wagtail_icons/templates/wagtail_icons/groups/index.html
wagtail_icons/templates/wagtail_icons/icons_page/add.html
wagtail_icons/templates/wagtail_icons/icons_page/edit.html
wagtail_icons/templates/wagtail_icons/icons_page/icons_header.html
wagtail_icons/templates/wagtail_icons/icons_page/icons_results.html
wagtail_icons/templates/wagtail_icons/icons_page/index.html
wagtail_icons/templates/wagtail_icons/templatetags/icon.html
wagtail_icons/templates/wagtail_icons/widgets/_listing_tab.html
wagtail_icons/templates/wagtail_icons/widgets/chooser_results.html
wagtail_icons/templates/wagtail_icons/widgets/icon_chooser.html
wagtail_icons/templatetags/__init__.py
wagtail_icons/templatetags/wagtail_icons_tags.py
wagtail_icons/views/__init__.py
wagtail_icons/views/chooser.py
wagtail_svg_icons-0.0.2.dist-info/LICENSE
wagtail_svg_icons-0.0.2.dist-info/METADATA
wagtail_svg_icons-0.0.2.dist-info/WHEEL
wagtail_svg_icons-0.0.2.dist-info/top_level.txt
wagtail_svg_icons-0.0.2.dist-info/RECORD
