Metadata-Version: 2.1
Name: wagtail-svg-icons
Version: 0.0.2
Summary: UNKNOWN
Home-page: https://github.com/LilJack118/wagtail_icons
Author: LilJack118
Author-email: jakub@kachange.com
License: UNKNOWN
Project-URL: Bug Tracker, https://github.com/LilJack118/wagtail_icons/issues
Keywords: wagtail django
Platform: UNKNOWN
Classifier: Programming Language :: Python :: 3
Classifier: License :: OSI Approved :: MIT License
Classifier: Operating System :: OS Independent
License-File: LICENSE
